{
  "default": [
    {
      "name": "Audio",
      "value": "7 speaker surround system"
    },
    {
      "name": "Roof",
      "value": "None"
    },
    {
      "name": "Floor mats",
      "value": "Carpet"
    },
    {
      "name": "Tyres",
      "value": "Summer tyres"
    },
    {
      "name": "Boot",
      "value": "None"
    },
    {
      "name": "Windows",
      "value": "None"
    },
    {
      "name": "Seats",
      "value": "None"
    },
    {
      "name": "Phone tech",
      "value": "None"
    }
  ],

  "options": [
    {
      "index": 0,
      "name": "Audio",
      "description": "Our premium audio systems",
      "base": "7 speaker surround system",
      "values": [
        { "value": "7 speaker surround system" },
        { "value": "12 speaker surround system" }
      ]
    },
    {
      "index": 1,
      "name": "Roof",
      "description": "Enhance the utility of your S90",
      "base": "None",
      "values": [
        { "value": "None" },
        { "value": "Bicycle carrier" },
        { "value": "Retractable ski carrier" },
        { "value": "85L roof box" }
      ]
    },
    {
      "index": 2,

      "name": "Floor mats",
      "description": "For convenience of cleaning",
      "base": "Carpet",
      "values": [
        { "value": "Carpet" },
        { "value": "Rubber - front only" },
        { "value": "Rubber - front and rear" }
      ]
    },
    {
      "index": 3,

      "name": "Tyres",
      "description": "Ensure your S90's capablities",
      "base": "Summer tyres",
      "values": [
        { "value": "Summer tyres" },
        { "value": "Winter tyres" },
        { "value": "Run flats" },
        { "value": "Economy tyres" }
      ]
    },
    {
      "index": 4,

      "name": "Boot",
      "description": "Prepare for any circumstance",
      "base": "None",
      "values": [
        { "value": "None" },
        { "value": "Cargo net" },
        { "value": "First aid kit" },
        { "value": "Fire extinguisher" },
        { "value": "Full safety package" }
      ]
    },
    {
      "index": 5,

      "name": "Windows",
      "description": "Combine style and function",
      "base": "None",
      "values": [
        { "value": "None" },
        { "value": "Light tint" },
        { "value": "Full tint" },
        { "value": "Rear sunshade package" }
      ]
    },
    {
      "index": 6,

      "name": "Seats",
      "description": "Make every drive a luxury",
      "base": "None",
      "values": [
        { "value": "None" },
        { "value": "Heated seats" },
        { "value": "Heated and cooling seats" },
        { "value": "Executive massage package" }
      ]
    },
    {
      "index": 7,

      "name": "Phone tech",
      "description": "Get the most accessibilty from your S90",
      "base": "None",
      "values": [
        { "value": "None" },
        { "value": "Wireless charging pad" },
        { "value": "Air vent phone holder" },
        { "value": "Phone as key module" }
      ]
    }
  ]
}
